am4894dev2/__init__.py
am4894dev2/am4894dev2.py
am4894dev2-0.1.0.dist-info/AUTHORS.rst
am4894dev2-0.1.0.dist-info/LICENSE
am4894dev2-0.1.0.dist-info/METADATA
am4894dev2-0.1.0.dist-info/WHEEL
am4894dev2-0.1.0.dist-info/top_level.txt
am4894dev2-0.1.0.dist-info/RECORD
